owasp_zap_historic/__init__.py
owasp_zap_historic/app.py
owasp_zap_historic/args.py
owasp_zap_historic/templates/alerts.html
owasp_zap_historic/templates/allalerts.html
owasp_zap_historic/templates/dashboard.html
owasp_zap_historic/templates/deldbconf.html
owasp_zap_historic/templates/deleconf.html
owasp_zap_historic/templates/ehistoric.html
owasp_zap_historic/templates/index.html
owasp_zap_historic/templates/login.html
owasp_zap_historic/templates/newdb.html
owasp_zap_historic/templates/redirect.html
owasp_zap_historic/templates/register.html
test/__init__.py
test/function_test.py
owasp_zap_historic-0.2.2.dist-info/LICENSE
owasp_zap_historic-0.2.2.dist-info/METADATA
owasp_zap_historic-0.2.2.dist-info/WHEEL
owasp_zap_historic-0.2.2.dist-info/entry_points.txt
owasp_zap_historic-0.2.2.dist-info/top_level.txt
owasp_zap_historic-0.2.2.dist-info/RECORD
