Metadata-Version: 2.1
Name: owasp-zap-historic
Version: 0.2.2
Summary: Custom report to display owasp zap historical execution records
Home-page: https://github.com/Accruent/owasp-zap-historic
Author: Neil Howell
Author-email: neiljhowell@gmail.com
License: GPL-3.0
Keywords: owasp zap historical execution report
Platform: UNKNOWN
Classifier: Framework :: Robot Framework
Classifier: Programming Language :: Python
Classifier: Topic :: Software Development :: Testing
License-File: LICENSE
Requires-Dist: bcrypt (~=3.2.0)
Requires-Dist: pytz (~=2021.3)
Requires-Dist: Flask (~=2.0.2)
Requires-Dist: setuptools (~=59.6.0)
Requires-Dist: pytest-cov
Requires-Dist: flask-mysqldb
Requires-Dist: config
